YouTube_controller/__init__.py
YouTube_controller/controller.py
YouTube_Contorller-0.1.dist-info/LICENSE
YouTube_Contorller-0.1.dist-info/METADATA
YouTube_Contorller-0.1.dist-info/WHEEL
YouTube_Contorller-0.1.dist-info/top_level.txt
YouTube_Contorller-0.1.dist-info/RECORD
