Metadata-Version: 2.1
Name: YouTube_Contorller
Version: 0.1
Classifier: Programming Language :: Python :: 3
Classifier: License :: OSI Approved :: MIT License
Classifier: Programming Language :: Python :: 3.6
Requires-Python: >=3.6
License-File: LICENSE
Requires-Dist: selenium >=4.0.0
